{
    "CodeList": [
        {
            "ValidValue": [
                {
                    "Code": "01",
                    "Value": "Closing Date",
                    "LastModified": "2017-09-01T06:02:02.687",
                    "IsDisabled": "No"
                },
                {
                    "Code": "02",
                    "Value": "Open Continuous",
                    "LastModified": "2017-09-01T06:02:02.703",
                    "IsDisabled": "No"
                },
                {
                    "Code": "03",
                    "Value": "Applicant Cut-Off",
                    "LastModified": "2017-09-01T06:02:02.72",
                    "IsDisabled": "No"
                },
                {
                    "Code": "04",
                    "Value": "Closing Time",
                    "LastModified": "2017-09-01T06:02:02.733",
                    "IsDisabled": "No"
                }
            ],
            "id": "AnnouncementClosingType"
        }
    ],
    "DateGenerated": "2023-09-30T20:31:23.793364Z"
}